[{"TransactionID": "TR-001", "Date": "05/24/2022", "Time": "07:12:26", "ProductID": "PROD-003", "Price": 917.79, "CustomerEmail": "yqpbtgtywm@example.com"}, {"TransactionID": "TR-002", "Date": "05/30/2022", "Time": "03:50:35", "ProductID": "PROD-002", "Price": 904.0, "CustomerEmail": "ysvvoxmyoh@example.com"}, {"TransactionID": "TR-003", "Date": "11/29/2022", "Time": "14:12:47", "ProductID": "PROD-006", "Price": 310.21, "CustomerEmail": "ugqickbbgt@example.com"}, {"TransactionID": "TR-004", "Date": "12/18/2022", "Time": "06:53:58", "ProductID": "PROD-010", "Price": 565.29, "CustomerEmail": "senzvunves@example.com"}, {"TransactionID": "TR-005", "Date": "07/17/2022", "Time": "21:16:08", "ProductID": "PROD-007", "Price": 597.81, "CustomerEmail": "fbkddcdyvu@example.com"}, {"TransactionID": "TR-006", "Date": "01/16/2023", "Time": "22:33:25", "ProductID": "PROD-009", "Price": 714.57, "CustomerEmail": "fhtjtjmpwu@example.com"}, {"TransactionID": "TR-007", "Date": "09/11/2022", "Time": "21:27:38", "ProductID": "PROD-001", "Price": 509.04, "CustomerEmail": "dnokpjmkpl@example.com"}, {"TransactionID": "TR-008", "Date": "10/01/2022", "Time": "10:43:13", "ProductID": "PROD-009", "Price": 203.88, "CustomerEmail": "rkxjjjamiu@example.com"}, {"TransactionID": "TR-009", "Date": "01/14/2023", "Time": "14:31:13", "ProductID": "PROD-001", "Price": 235.23, "CustomerEmail": "euarpaoqam@example.com"}, {"TransactionID": "TR-010", "Date": "08/26/2022", "Time": "16:34:08", "ProductID": "PROD-009", "Price": 273.9, "CustomerEmail": "rtidsliinj@example.com"}, {"TransactionID": "TR-011", "Date": "10/31/2022", "Time": "05:36:36", "ProductID": "PROD-008", "Price": 62.4, "CustomerEmail": "mrxqkypkdz@example.com"}, {"TransactionID": "TR-012", "Date": "03/23/2023", "Time": "13:03:17", "ProductID": "PROD-008", "Price": 705.94, "CustomerEmail": "bthqiojjkl@example.com"}, {"TransactionID": "TR-013", "Date": "10/20/2022", "Time": "13:33:12", "ProductID": "PROD-006", "Price": 619.59, "CustomerEmail": "xpbmfwxqfp@example.com"}, {"TransactionID": "TR-014", "Date": "03/13/2023", "Time": null, "ProductID": "PROD-003", "Price": 903.93, "CustomerEmail": "oxshozhacn@example.com"}, {"TransactionID": "TR-015", "Date": "04/07/2023", "Time": "07:33:53", "ProductID": "PROD-009", "Price": 609.98, "CustomerEmail": "pspxboglgm@example.com"}, {"TransactionID": "TR-016", "Date": "01/29/2023", "Time": "07:08:55", "ProductID": "PROD-004", "Price": 613.1, "CustomerEmail": "wllgqkzjau@example.com"}, {"TransactionID": "TR-017", "Date": "12/30/2022", "Time": "14:11:13", "ProductID": "PROD-001", "Price": 794.89, "CustomerEmail": "fbkddcdyvu@example.com"}, {"TransactionID": "TR-018", "Date": "05/21/2022", "Time": "02:39:57", "ProductID": "PROD-002", "Price": 812.37, "CustomerEmail": "dnokpjmkpl@example.com"}, {"TransactionID": "TR-019", "Date": "12/02/2022", "Time": "10:51:10", "ProductID": "PROD-008", "Price": 821.45, "CustomerEmail": "aecuwbuejj@example.com"}, {"TransactionID": "TR-020", "Date": "02/20/2023", "Time": "00:05:15", "ProductID": "PROD-003", "Price": 192.27, "CustomerEmail": "isllmsvhil@example.com"}, {"TransactionID": "TR-021", "Date": "07/26/2022", "Time": "22:02:36", "ProductID": "PROD-001", "Price": 924.52, "CustomerEmail": "zwjocmzdos@example.com"}, {"TransactionID": "TR-022", "Date": "10/12/2022", "Time": "01:41:40", "ProductID": "PROD-006", "Price": 638.77, "CustomerEmail": "oxshozhacn@example.com"}, {"TransactionID": "TR-023", "Date": "01/04/2023", "Time": "21:41:32", "ProductID": "PROD-004", "Price": 339.12, "CustomerEmail": "ospvmyrulg@example.com"}, {"TransactionID": "TR-024", "Date": "07/13/2022", "Time": "19:11:30", "ProductID": "PROD-007", "Price": 143.89, "CustomerEmail": "bsszhozlvk@example.com"}, {"TransactionID": "TR-025", "Date": "01/28/2023", "Time": "05:54:42", "ProductID": "PROD-003", "Price": 493.41, "CustomerEmail": "drnyzjxtrc@example.com"}, {"TransactionID": "TR-026", "Date": "01/25/2023", "Time": "14:44:04", "ProductID": "PROD-006", "Price": 499.59, "CustomerEmail": "klualfzehr@example.com"}, {"TransactionID": "TR-027", "Date": "09/22/2022", "Time": "18:24:09", "ProductID": "PROD-007", "Price": 40.06, "CustomerEmail": "jsohyotfoy@example.com"}, {"TransactionID": "TR-028", "Date": "06/09/2022", "Time": "15:51:39", "ProductID": "PROD-007", "Price": 617.87, "CustomerEmail": "drnyzjxtrc@example.com"}, {"TransactionID": "TR-029", "Date": "12/07/2022", "Time": "03:13:46", "ProductID": "PROD-009", "Price": 812.47, "CustomerEmail": "xoocrqmtax@example.com"}, {"TransactionID": "TR-030", "Date": "05/24/2022", "Time": "09:00:01", "ProductID": "PROD-010", "Price": 626.37, "CustomerEmail": "suecsqnvaq@example.com"}, {"TransactionID": "TR-031", "Date": "10/29/2022", "Time": "17:44:42", "ProductID": "PROD-006", "Price": 874.92, "CustomerEmail": "vmndvqwoao@example.com"}, {"TransactionID": "TR-032", "Date": "07/17/2022", "Time": "22:59:40", "ProductID": "PROD-003", "Price": 743.29, "CustomerEmail": "vqeamysxou@example.com"}, {"TransactionID": "TR-033", "Date": "05/05/2023", "Time": "02:27:40", "ProductID": "PROD-009", "Price": 305.88, "CustomerEmail": "ywsipgrpah@example.com"}, {"TransactionID": "TR-034", "Date": "10/23/2022", "Time": "05:31:51", "ProductID": "PROD-008", "Price": 823.0, "CustomerEmail": "haqbcsaeep@example.com"}, {"TransactionID": "TR-035", "Date": "06/28/2022", "Time": "00:32:51", "ProductID": "PROD-007", "Price": 397.59, "CustomerEmail": "yqpbtgtywm@example.com"}, {"TransactionID": "TR-036", "Date": "08/06/2022", "Time": "06:33:42", "ProductID": "PROD-005", "Price": 547.59, "CustomerEmail": "vmndvqwoao@example.com"}, {"TransactionID": "TR-037", "Date": null, "Time": "17:30:31", "ProductID": "PROD-009", "Price": 849.11, "CustomerEmail": "iyjpkmeanw@example.com"}, {"TransactionID": "TR-038", "Date": "06/16/2022", "Time": "09:28:40", "ProductID": "PROD-003", "Price": 48.79, "CustomerEmail": "vcawslbbns@example.com"}, {"TransactionID": "TR-039", "Date": "06/22/2022", "Time": "07:51:35", "ProductID": "PROD-010", "Price": 368.16, "CustomerEmail": "wllgqkzjau@example.com"}, {"TransactionID": "TR-040", "Date": "05/07/2023", "Time": "09:57:50", "ProductID": "PROD-007", "Price": 806.6, "CustomerEmail": "eepalkxwqu@example.com"}, {"TransactionID": "TR-041", "Date": "10/29/2022", "Time": "15:41:05", "ProductID": "PROD-007", "Price": 781.45, "CustomerEmail": "qofbrdlmxd@example.com"}, {"TransactionID": "TR-042", "Date": "05/14/2022", "Time": "16:17:07", "ProductID": "PROD-004", "Price": 608.78, "CustomerEmail": "zwjocmzdos@example.com"}, {"TransactionID": "TR-043", "Date": "02/28/2023", "Time": "09:13:00", "ProductID": "PROD-004", "Price": 776.22, "CustomerEmail": "mendhlfsin@example.com"}, {"TransactionID": "TR-044", "Date": "01/08/2023", "Time": "00:17:09", "ProductID": "PROD-005", "Price": 766.69, "CustomerEmail": "dygmnhslsm@example.com"}, {"TransactionID": "TR-045", "Date": "01/14/2023", "Time": "14:00:18", "ProductID": "PROD-009", "Price": 805.64, "CustomerEmail": "drnyzjxtrc@example.com"}, {"TransactionID": "TR-046", "Date": "12/28/2022", "Time": "04:36:05", "ProductID": "PROD-003", "Price": 250.57, "CustomerEmail": "izmpaugzqi@example.com"}, {"TransactionID": "TR-047", "Date": "03/02/2023", "Time": "15:16:57", "ProductID": "PROD-009", "Price": 460.17, "CustomerEmail": "ddovifkziv@example.com"}, {"TransactionID": "TR-048", "Date": "06/24/2022", "Time": "07:53:07", "ProductID": "PROD-009", "Price": 994.38, "CustomerEmail": "ysvvoxmyoh@example.com"}, {"TransactionID": "TR-049", "Date": "06/11/2022", "Time": "23:16:24", "ProductID": "PROD-006", "Price": 480.59, "CustomerEmail": "qpesinztxm@example.com"}, {"TransactionID": "TR-050", "Date": "05/10/2023", "Time": "09:02:39", "ProductID": "PROD-001", "Price": 831.76, "CustomerEmail": "rawopnnlvu@example.com"}, {"TransactionID": "TR-051", "Date": "12/05/2022", "Time": "02:32:36", "ProductID": "PROD-004", "Price": 15.62, "CustomerEmail": "qofbrdlmxd@example.com"}, {"TransactionID": "TR-052", "Date": "03/12/2023", "Time": "18:25:53", "ProductID": "PROD-010", "Price": 398.85, "CustomerEmail": "ezrukqagsm@example.com"}, {"TransactionID": "TR-053", "Date": "08/14/2022", "Time": "01:16:41", "ProductID": "PROD-010", "Price": 321.02, "CustomerEmail": "dfqryoefeg@example.com"}, {"TransactionID": "TR-054", "Date": "02/23/2023", "Time": "02:41:29", "ProductID": "PROD-007", "Price": 425.02, "CustomerEmail": "dlyqweyyke@example.com"}, {"TransactionID": "TR-055", "Date": "12/14/2022", "Time": "07:47:11", "ProductID": "PROD-005", "Price": 854.6, "CustomerEmail": "pspxboglgm@example.com"}, {"TransactionID": "TR-056", "Date": "03/27/2023", "Time": "16:52:18", "ProductID": "PROD-003", "Price": 563.35, "CustomerEmail": "xoocrqmtax@example.com"}, {"TransactionID": "TR-057", "Date": "11/05/2022", "Time": "11:09:13", "ProductID": "PROD-007", "Price": 340.39, "CustomerEmail": "thnwqoxyrt@example.com"}, {"TransactionID": "TR-058", "Date": "03/04/2023", "Time": "06:32:15", "ProductID": "PROD-007", "Price": 735.24, "CustomerEmail": "tyqbqtebpl@example.com"}, {"TransactionID": "TR-059", "Date": "11/13/2022", "Time": "08:06:43", "ProductID": "PROD-002", "Price": 868.49, "CustomerEmail": "gisshlxfng@example.com"}, {"TransactionID": "TR-060", "Date": "07/14/2022", "Time": "00:30:09", "ProductID": "PROD-008", "Price": 415.71, "CustomerEmail": "kpnqriumlk@example.com"}, {"TransactionID": "TR-061", "Date": "08/01/2022", "Time": "07:09:58", "ProductID": "PROD-005", "Price": 512.47, "CustomerEmail": "qofbrdlmxd@example.com"}, {"TransactionID": "TR-062", "Date": "06/20/2022", "Time": "00:47:10", "ProductID": "PROD-007", "Price": 610.38, "CustomerEmail": "jsohyotfoy@example.com"}, {"TransactionID": "TR-063", "Date": "10/01/2022", "Time": "05:35:26", "ProductID": "PROD-010", "Price": 471.12, "CustomerEmail": "biziysiyeh@example.com"}, {"TransactionID": "TR-064", "Date": "02/24/2023", "Time": "09:13:35", "ProductID": "PROD-002", "Price": 731.11, "CustomerEmail": "pspxboglgm@example.com"}, {"TransactionID": "TR-065", "Date": "11/23/2022", "Time": "04:39:14", "ProductID": "PROD-004", "Price": 319.3, "CustomerEmail": "oijsdnavny@example.com"}, {"TransactionID": "TR-066", "Date": null, "Time": "14:59:25", "ProductID": "PROD-007", "Price": 885.09, "CustomerEmail": "fbkddcdyvu@example.com"}, {"TransactionID": "TR-067", "Date": "01/16/2023", "Time": "18:23:29", "ProductID": "PROD-008", "Price": 34.29, "CustomerEmail": "thnwqoxyrt@example.com"}, {"TransactionID": "TR-068", "Date": "07/13/2022", "Time": "21:06:08", "ProductID": "PROD-005", "Price": 565.52, "CustomerEmail": "euarpaoqam@example.com"}, {"TransactionID": "TR-069", "Date": "02/19/2023", "Time": "02:58:24", "ProductID": "PROD-007", "Price": 305.62, "CustomerEmail": "ccwyhqgzzs@example.com"}, {"TransactionID": "TR-070", "Date": "11/06/2022", "Time": "01:00:47", "ProductID": "PROD-010", "Price": 69.96, "CustomerEmail": "senzvunves@example.com"}, {"TransactionID": "TR-071", "Date": "04/10/2023", "Time": "04:04:34", "ProductID": "PROD-007", "Price": 547.27, "CustomerEmail": "rmzskpitoq@example.com"}, {"TransactionID": "TR-072", "Date": "11/01/2022", "Time": "14:35:15", "ProductID": "PROD-006", "Price": 177.07, "CustomerEmail": "vcawslbbns@example.com"}, {"TransactionID": "TR-073", "Date": "01/10/2023", "Time": "12:52:46", "ProductID": "PROD-003", "Price": 709.16, "CustomerEmail": "qaftzsjfao@example.com"}, {"TransactionID": "TR-074", "Date": "03/17/2023", "Time": "18:39:02", "ProductID": "PROD-010", "Price": 498.88, "CustomerEmail": "lngcfmewek@example.com"}, {"TransactionID": "TR-075", "Date": "09/08/2022", "Time": "07:58:13", "ProductID": "PROD-009", "Price": 283.5, "CustomerEmail": "bthqiojjkl@example.com"}, {"TransactionID": "TR-076", "Date": "10/13/2022", "Time": "06:16:55", "ProductID": "PROD-005", "Price": 312.05, "CustomerEmail": "bksreixctc@example.com"}, {"TransactionID": "TR-077", "Date": "03/07/2023", "Time": "20:01:55", "ProductID": "PROD-008", "Price": 750.79, "CustomerEmail": "klualfzehr@example.com"}, {"TransactionID": "TR-078", "Date": "12/07/2022", "Time": "16:10:49", "ProductID": "PROD-004", "Price": 200.25, "CustomerEmail": "wepwbgadhn@example.com"}, {"TransactionID": "TR-079", "Date": "03/14/2023", "Time": "17:49:21", "ProductID": "PROD-007", "Price": 273.33, "CustomerEmail": "rtidsliinj@example.com"}, {"TransactionID": "TR-080", "Date": "12/27/2022", "Time": "04:56:20", "ProductID": "PROD-008", "Price": null, "CustomerEmail": "tqnsfcniak@example.com"}, {"TransactionID": "TR-081", "Date": "10/12/2022", "Time": "12:38:28", "ProductID": "PROD-010", "Price": 988.05, "CustomerEmail": "iyjpkmeanw@example.com"}, {"TransactionID": "TR-082", "Date": "12/01/2022", "Time": "20:30:19", "ProductID": "PROD-007", "Price": 934.99, "CustomerEmail": "fcqvypggpb@example.com"}, {"TransactionID": "TR-083", "Date": "01/19/2023", "Time": "21:32:47", "ProductID": "PROD-005", "Price": 106.73, "CustomerEmail": "igrowkcazi@example.com"}, {"TransactionID": "TR-084", "Date": "01/06/2023", "Time": "12:35:39", "ProductID": "PROD-007", "Price": 444.19, "CustomerEmail": "bnazqauvzc@example.com"}, {"TransactionID": "TR-085", "Date": "02/21/2023", "Time": "13:49:20", "ProductID": "PROD-008", "Price": 647.26, "CustomerEmail": "biziysiyeh@example.com"}, {"TransactionID": "TR-086", "Date": "11/28/2022", "Time": "07:42:57", "ProductID": "PROD-008", "Price": 796.12, "CustomerEmail": "vmyftqmsyt@example.com"}, {"TransactionID": "TR-087", "Date": "07/13/2022", "Time": "15:37:07", "ProductID": "PROD-003", "Price": 431.4, "CustomerEmail": "wrwzcvdefd@example.com"}, {"TransactionID": "TR-088", "Date": "09/16/2022", "Time": "04:05:00", "ProductID": "PROD-003", "Price": 121.98, "CustomerEmail": "wpfczlicue@example.com"}, {"TransactionID": "TR-089", "Date": "03/01/2023", "Time": "03:50:55", "ProductID": "PROD-006", "Price": 740.11, "CustomerEmail": "isllmsvhil@example.com"}, {"TransactionID": "TR-090", "Date": "11/05/2022", "Time": "13:37:20", "ProductID": "PROD-007", "Price": 387.99, "CustomerEmail": "fbkddcdyvu@example.com"}, {"TransactionID": "TR-091", "Date": "08/08/2022", "Time": "07:20:07", "ProductID": "PROD-001", "Price": 694.1, "CustomerEmail": "kremphtwkp@example.com"}, {"TransactionID": "TR-092", "Date": "02/26/2023", "Time": "09:02:25", "ProductID": "PROD-010", "Price": 460.73, "CustomerEmail": "rmzskpitoq@example.com"}, {"TransactionID": "TR-093", "Date": "11/25/2022", "Time": "09:19:19", "ProductID": "PROD-003", "Price": 355.01, "CustomerEmail": "rtwobqnfmg@example.com"}, {"TransactionID": "TR-094", "Date": "01/02/2023", "Time": "08:17:47", "ProductID": "PROD-003", "Price": 528.87, "CustomerEmail": "oxshozhacn@example.com"}, {"TransactionID": "TR-095", "Date": "12/23/2022", "Time": "17:31:04", "ProductID": "PROD-006", "Price": 887.42, "CustomerEmail": "ezrukqagsm@example.com"}, {"TransactionID": "TR-096", "Date": "09/17/2022", "Time": "03:21:43", "ProductID": "PROD-003", "Price": 804.19, "CustomerEmail": "waoawphybi@example.com"}, {"TransactionID": "TR-097", "Date": "12/27/2022", "Time": "23:21:52", "ProductID": "PROD-010", "Price": 16.01, "CustomerEmail": "hehovffjua@example.com"}, {"TransactionID": "TR-098", "Date": "01/24/2023", "Time": "15:28:38", "ProductID": "PROD-007", "Price": 396.7, "CustomerEmail": "zpuhtnpvxn@example.com"}, {"TransactionID": "TR-099", "Date": "01/18/2023", "Time": "04:23:45", "ProductID": "PROD-006", "Price": 855.43, "CustomerEmail": "xoocrqmtax@example.com"}, {"TransactionID": "TR-100", "Date": "06/03/2022", "Time": "23:55:26", "ProductID": "PROD-007", "Price": 108.27, "CustomerEmail": "hyqfdcapdp@example.com"}, {"TransactionID": "TR-101", "Date": "07/31/2022", "Time": "03:21:14", "ProductID": "PROD-005", "Price": 440.05, "CustomerEmail": "wrwzcvdefd@example.com"}, {"TransactionID": "TR-102", "Date": "08/18/2022", "Time": "14:08:15", "ProductID": "PROD-002", "Price": 431.17, "CustomerEmail": "hehovffjua@example.com"}, {"TransactionID": "TR-103", "Date": "12/10/2022", "Time": "20:27:00", "ProductID": "PROD-002", "Price": 731.65, "CustomerEmail": "hyqfdcapdp@example.com"}, {"TransactionID": "TR-104", "Date": "12/14/2022", "Time": "12:17:37", "ProductID": "PROD-005", "Price": 58.47, "CustomerEmail": "ugqickbbgt@example.com"}, {"TransactionID": "TR-105", "Date": "05/03/2023", "Time": "23:08:52", "ProductID": null, "Price": 643.4, "CustomerEmail": "ezrukqagsm@example.com"}, {"TransactionID": "TR-106", "Date": "11/09/2022", "Time": "11:42:51", "ProductID": "PROD-001", "Price": 185.13, "CustomerEmail": "ohvgorgcfj@example.com"}, {"TransactionID": "TR-107", "Date": "03/16/2023", "Time": "06:39:48", "ProductID": "PROD-002", "Price": 139.05, "CustomerEmail": "drnyzjxtrc@example.com"}, {"TransactionID": "TR-108", "Date": "06/22/2022", "Time": "10:01:23", "ProductID": "PROD-001", "Price": 956.93, "CustomerEmail": "vyolfxyquk@example.com"}, {"TransactionID": "TR-109", "Date": "04/09/2023", "Time": "00:24:47", "ProductID": "PROD-003", "Price": 233.39, "CustomerEmail": "dmpqxyuxod@example.com"}, {"TransactionID": "TR-110", "Date": "09/24/2022", "Time": "23:17:08", "ProductID": "PROD-010", "Price": 942.33, "CustomerEmail": "mrxqkypkdz@example.com"}, {"TransactionID": "TR-111", "Date": "03/08/2023", "Time": "12:12:59", "ProductID": "PROD-007", "Price": 448.08, "CustomerEmail": "haqbcsaeep@example.com"}, {"TransactionID": "TR-112", "Date": "05/01/2023", "Time": "04:38:41", "ProductID": "PROD-002", "Price": 837.92, "CustomerEmail": "yqpbtgtywm@example.com"}, {"TransactionID": "TR-113", "Date": "07/22/2022", "Time": "11:09:39", "ProductID": "PROD-002", "Price": 378.47, "CustomerEmail": "fbkddcdyvu@example.com"}, {"TransactionID": "TR-114", "Date": "03/20/2023", "Time": "13:26:03", "ProductID": "PROD-006", "Price": 499.39, "CustomerEmail": "ospvmyrulg@example.com"}, {"TransactionID": "TR-115", "Date": "04/27/2023", "Time": "10:18:33", "ProductID": "PROD-009", "Price": 76.71, "CustomerEmail": "eepalkxwqu@example.com"}, {"TransactionID": "TR-116", "Date": "06/30/2022", "Time": "10:01:16", "ProductID": "PROD-004", "Price": 958.08, "CustomerEmail": "wrwzcvdefd@example.com"}, {"TransactionID": "TR-117", "Date": "06/26/2022", "Time": "04:11:23", "ProductID": "PROD-007", "Price": 343.2, "CustomerEmail": "pughqjoxqh@example.com"}, {"TransactionID": "TR-118", "Date": "03/26/2023", "Time": "07:18:02", "ProductID": "PROD-005", "Price": 153.47, "CustomerEmail": "sdtuwacsvc@example.com"}, {"TransactionID": "TR-119", "Date": "08/10/2022", "Time": "04:42:45", "ProductID": "PROD-007", "Price": 628.5, "CustomerEmail": "jsohyotfoy@example.com"}, {"TransactionID": "TR-120", "Date": "07/11/2022", "Time": "09:33:51", "ProductID": "PROD-003", "Price": 886.22, "CustomerEmail": "vbcuxateyx@example.com"}, {"TransactionID": "TR-121", "Date": "05/18/2022", "Time": "12:48:54", "ProductID": "PROD-010", "Price": 40.85, "CustomerEmail": "vcawslbbns@example.com"}, {"TransactionID": "TR-122", "Date": "09/08/2022", "Time": "13:40:05", "ProductID": "PROD-002", "Price": 200.3, "CustomerEmail": "igrowkcazi@example.com"}, {"TransactionID": "TR-123", "Date": "07/06/2022", "Time": "06:04:16", "ProductID": "PROD-001", "Price": 853.22, "CustomerEmail": "taljhnykmw@example.com"}, {"TransactionID": "TR-124", "Date": "01/15/2023", "Time": "07:20:48", "ProductID": "PROD-003", "Price": 791.65, "CustomerEmail": "qpesinztxm@example.com"}, {"TransactionID": "TR-125", "Date": "01/06/2023", "Time": "21:11:50", "ProductID": "PROD-003", "Price": 334.15, "CustomerEmail": "klualfzehr@example.com"}, {"TransactionID": "TR-126", "Date": "10/16/2022", "Time": "03:16:52", "ProductID": "PROD-007", "Price": 867.67, "CustomerEmail": "zwvzhfvjdq@example.com"}, {"TransactionID": "TR-127", "Date": "03/13/2023", "Time": "15:51:18", "ProductID": "PROD-010", "Price": 173.96, "CustomerEmail": "vxzrmxfzij@example.com"}, {"TransactionID": "TR-128", "Date": "06/05/2022", "Time": "08:40:03", "ProductID": "PROD-008", "Price": 155.63, "CustomerEmail": "qofbrdlmxd@example.com"}, {"TransactionID": "TR-129", "Date": "02/15/2023", "Time": "09:41:01", "ProductID": "PROD-004", "Price": 101.65, "CustomerEmail": "kremphtwkp@example.com"}, {"TransactionID": "TR-130", "Date": "01/28/2023", "Time": "14:03:46", "ProductID": "PROD-002", "Price": 838.81, "CustomerEmail": "sakyrgxhro@example.com"}, {"TransactionID": "TR-131", "Date": "04/03/2023", "Time": "13:38:40", "ProductID": "PROD-008", "Price": 837.95, "CustomerEmail": "drnyzjxtrc@example.com"}, {"TransactionID": "TR-132", "Date": "03/29/2023", "Time": "01:12:51", "ProductID": "PROD-009", "Price": 561.36, "CustomerEmail": "qpesinztxm@example.com"}, {"TransactionID": "TR-133", "Date": "10/31/2022", "Time": "19:21:27", "ProductID": "PROD-008", "Price": 489.43, "CustomerEmail": "drnyzjxtrc@example.com"}, {"TransactionID": "TR-134", "Date": "02/14/2023", "Time": "09:25:50", "ProductID": "PROD-003", "Price": 819.93, "CustomerEmail": "vyolfxyquk@example.com"}, {"TransactionID": "TR-135", "Date": "01/21/2023", "Time": "06:28:04", "ProductID": "PROD-004", "Price": 393.48, "CustomerEmail": "ohvgorgcfj@example.com"}, {"TransactionID": "TR-136", "Date": "11/03/2022", "Time": "10:09:26", "ProductID": "PROD-007", "Price": 279.94, "CustomerEmail": "ospvmyrulg@example.com"}, {"TransactionID": "TR-137", "Date": "10/05/2022", "Time": "22:36:15", "ProductID": "PROD-007", "Price": 454.21, "CustomerEmail": "lxfoxoihpv@example.com"}, {"TransactionID": "TR-138", "Date": "01/12/2023", "Time": "19:01:05", "ProductID": "PROD-005", "Price": null, "CustomerEmail": "dfqryoefeg@example.com"}, {"TransactionID": "TR-139", "Date": "09/06/2022", "Time": "22:57:33", "ProductID": "PROD-005", "Price": 795.36, "CustomerEmail": "eepalkxwqu@example.com"}, {"TransactionID": "TR-140", "Date": "07/09/2022", "Time": "17:49:34", "ProductID": "PROD-001", "Price": 53.41, "CustomerEmail": "isllmsvhil@example.com"}, {"TransactionID": "TR-141", "Date": "04/13/2023", "Time": "13:27:53", "ProductID": "PROD-008", "Price": 262.12, "CustomerEmail": "ddovifkziv@example.com"}, {"TransactionID": "TR-142", "Date": "11/11/2022", "Time": "20:53:16", "ProductID": "PROD-001", "Price": 979.56, "CustomerEmail": "vlnuasgscp@example.com"}, {"TransactionID": "TR-143", "Date": "11/13/2022", "Time": "04:14:03", "ProductID": "PROD-009", "Price": 399.59, "CustomerEmail": "igrowkcazi@example.com"}, {"TransactionID": "TR-144", "Date": "03/15/2023", "Time": "03:19:44", "ProductID": "PROD-010", "Price": 397.46, "CustomerEmail": "rmzskpitoq@example.com"}, {"TransactionID": "TR-145", "Date": "10/01/2022", "Time": "15:48:45", "ProductID": "PROD-006", "Price": 613.11, "CustomerEmail": "aecuwbuejj@example.com"}, {"TransactionID": "TR-146", "Date": "11/29/2022", "Time": "01:40:30", "ProductID": "PROD-007", "Price": 436.54, "CustomerEmail": "rtidsliinj@example.com"}, {"TransactionID": "TR-147", "Date": "10/23/2022", "Time": "00:52:21", "ProductID": "PROD-001", "Price": 283.02, "CustomerEmail": "vxzrmxfzij@example.com"}, {"TransactionID": "TR-148", "Date": "09/30/2022", "Time": "20:44:02", "ProductID": "PROD-005", "Price": 866.05, "CustomerEmail": "rawopnnlvu@example.com"}, {"TransactionID": "TR-149", "Date": "05/19/2022", "Time": "10:18:48", "ProductID": "PROD-003", "Price": 962.5, "CustomerEmail": "fhtjtjmpwu@example.com"}, {"TransactionID": "TR-150", "Date": "05/10/2023", "Time": "12:02:59", "ProductID": "PROD-009", "Price": 745.38, "CustomerEmail": "efkhuyhdek@example.com"}, {"TransactionID": "TR-151", "Date": "09/29/2022", "Time": "03:38:26", "ProductID": "PROD-008", "Price": 199.86, "CustomerEmail": "sakyrgxhro@example.com"}, {"TransactionID": "TR-152", "Date": "12/10/2022", "Time": "17:54:49", "ProductID": "PROD-005", "Price": 511.29, "CustomerEmail": "bksreixctc@example.com"}, {"TransactionID": "TR-153", "Date": "02/15/2023", "Time": "23:54:45", "ProductID": "PROD-008", "Price": 340.36, "CustomerEmail": "vrcxwykwbn@example.com"}, {"TransactionID": "TR-154", "Date": "03/19/2023", "Time": "18:23:58", "ProductID": "PROD-010", "Price": 190.21, "CustomerEmail": "ohvgorgcfj@example.com"}, {"TransactionID": "TR-155", "Date": "07/07/2022", "Time": "08:50:17", "ProductID": "PROD-002", "Price": 399.0, "CustomerEmail": "mzyjrjaftr@example.com"}, {"TransactionID": "TR-156", "Date": "11/30/2022", "Time": "10:01:57", "ProductID": "PROD-005", "Price": 379.35, "CustomerEmail": "bnazqauvzc@example.com"}, {"TransactionID": "TR-157", "Date": "11/16/2022", "Time": "16:20:21", "ProductID": "PROD-008", "Price": 535.76, "CustomerEmail": "klualfzehr@example.com"}, {"TransactionID": "TR-158", "Date": "05/21/2022", "Time": "14:12:40", "ProductID": "PROD-005", "Price": 192.75, "CustomerEmail": "wpfczlicue@example.com"}, {"TransactionID": "TR-159", "Date": "06/24/2022", "Time": "16:33:54", "ProductID": "PROD-007", "Price": 575.09, "CustomerEmail": "ugqickbbgt@example.com"}, {"TransactionID": "TR-160", "Date": "03/25/2023", "Time": "05:26:02", "ProductID": "PROD-005", "Price": 179.1, "CustomerEmail": "fhkuehkiej@example.com"}, {"TransactionID": "TR-161", "Date": "12/08/2022", "Time": "20:26:20", "ProductID": "PROD-003", "Price": 291.3, "CustomerEmail": "zpuhtnpvxn@example.com"}, {"TransactionID": "TR-162", "Date": "05/21/2022", "Time": "05:49:16", "ProductID": "PROD-003", "Price": 277.49, "CustomerEmail": "twflmapedl@example.com"}, {"TransactionID": "TR-163", "Date": "08/07/2022", "Time": "00:14:20", "ProductID": "PROD-009", "Price": 119.44, "CustomerEmail": "sakyrgxhro@example.com"}, {"TransactionID": "TR-164", "Date": "11/06/2022", "Time": "10:21:19", "ProductID": "PROD-004", "Price": 269.3, "CustomerEmail": "qaftzsjfao@example.com"}, {"TransactionID": "TR-165", "Date": "01/28/2023", "Time": "04:14:19", "ProductID": "PROD-003", "Price": null, "CustomerEmail": "vwxctibmlr@example.com"}, {"TransactionID": "TR-166", "Date": "01/28/2023", "Time": "07:09:14", "ProductID": "PROD-002", "Price": 448.65, "CustomerEmail": "ywsipgrpah@example.com"}, {"TransactionID": "TR-167", "Date": "06/20/2022", "Time": "02:45:08", "ProductID": "PROD-006", "Price": 803.77, "CustomerEmail": "yqpbtgtywm@example.com"}, {"TransactionID": "TR-168", "Date": "08/14/2022", "Time": "12:56:34", "ProductID": "PROD-007", "Price": 690.85, "CustomerEmail": "zpuhtnpvxn@example.com"}, {"TransactionID": "TR-169", "Date": "07/10/2022", "Time": "03:44:42", "ProductID": "PROD-008", "Price": 206.4, "CustomerEmail": "klualfzehr@example.com"}, {"TransactionID": "TR-170", "Date": "03/21/2023", "Time": "23:46:41", "ProductID": "PROD-006", "Price": 567.86, "CustomerEmail": "bthqiojjkl@example.com"}, {"TransactionID": "TR-171", "Date": "01/05/2023", "Time": "18:26:30", "ProductID": "PROD-002", "Price": 890.24, "CustomerEmail": "hehovffjua@example.com"}, {"TransactionID": "TR-172", "Date": "02/23/2023", "Time": "12:28:48", "ProductID": "PROD-010", "Price": 977.74, "CustomerEmail": "dlyqweyyke@example.com"}, {"TransactionID": "TR-173", "Date": "12/20/2022", "Time": "11:57:11", "ProductID": "PROD-003", "Price": 914.21, "CustomerEmail": "efkhuyhdek@example.com"}, {"TransactionID": "TR-174", "Date": "04/01/2023", "Time": "15:48:39", "ProductID": "PROD-007", "Price": 209.89, "CustomerEmail": "klualfzehr@example.com"}, {"TransactionID": "TR-175", "Date": "02/15/2023", "Time": "10:19:34", "ProductID": "PROD-009", "Price": 273.07, "CustomerEmail": "eepalkxwqu@example.com"}, {"TransactionID": "TR-176", "Date": "05/26/2022", "Time": "22:33:52", "ProductID": "PROD-007", "Price": 50.43, "CustomerEmail": "wjmyxmawbw@example.com"}, {"TransactionID": "TR-177", "Date": "03/04/2023", "Time": "06:14:07", "ProductID": "PROD-006", "Price": 690.58, "CustomerEmail": "ccwyhqgzzs@example.com"}, {"TransactionID": "TR-178", "Date": "08/05/2022", "Time": "20:47:36", "ProductID": "PROD-009", "Price": 368.31, "CustomerEmail": "pspxboglgm@example.com"}, {"TransactionID": "TR-179", "Date": "01/12/2023", "Time": "16:05:01", "ProductID": "PROD-005", "Price": 651.1, "CustomerEmail": "drnyzjxtrc@example.com"}, {"TransactionID": "TR-180", "Date": "12/15/2022", "Time": "10:57:08", "ProductID": "PROD-006", "Price": 312.85, "CustomerEmail": "oijsdnavny@example.com"}, {"TransactionID": "TR-181", "Date": "02/08/2023", "Time": "12:40:38", "ProductID": "PROD-001", "Price": 600.4, "CustomerEmail": "suecsqnvaq@example.com"}, {"TransactionID": "TR-182", "Date": "12/12/2022", "Time": "17:15:38", "ProductID": "PROD-001", "Price": 386.15, "CustomerEmail": "dkqgjzzaws@example.com"}, {"TransactionID": "TR-183", "Date": "03/28/2023", "Time": "20:36:21", "ProductID": "PROD-009", "Price": 227.24, "CustomerEmail": "qofbrdlmxd@example.com"}, {"TransactionID": "TR-184", "Date": "04/17/2023", "Time": "16:36:28", "ProductID": "PROD-008", "Price": 92.97, "CustomerEmail": "wepwbgadhn@example.com"}, {"TransactionID": "TR-185", "Date": "02/02/2023", "Time": "02:02:10", "ProductID": "PROD-005", "Price": 835.11, "CustomerEmail": "gisshlxfng@example.com"}, {"TransactionID": "TR-186", "Date": "12/28/2022", "Time": "08:59:50", "ProductID": "PROD-003", "Price": 106.86, "CustomerEmail": "wllgqkzjau@example.com"}, {"TransactionID": "TR-187", "Date": "05/14/2022", "Time": "05:19:46", "ProductID": "PROD-006", "Price": 795.99, "CustomerEmail": "waoawphybi@example.com"}, {"TransactionID": "TR-188", "Date": "05/14/2022", "Time": "17:50:24", "ProductID": "PROD-002", "Price": 505.18, "CustomerEmail": "bqnybeyjyd@example.com"}, {"TransactionID": "TR-189", "Date": "04/07/2023", "Time": "18:46:07", "ProductID": "PROD-009", "Price": 617.15, "CustomerEmail": "mzyjrjaftr@example.com"}, {"TransactionID": "TR-190", "Date": "02/13/2023", "Time": "23:27:31", "ProductID": "PROD-008", "Price": 335.36, "CustomerEmail": "iyjpkmeanw@example.com"}, {"TransactionID": "TR-191", "Date": "07/28/2022", "Time": "05:07:15", "ProductID": "PROD-010", "Price": 306.13, "CustomerEmail": "waoawphybi@example.com"}, {"TransactionID": "TR-192", "Date": "05/22/2022", "Time": "10:09:26", "ProductID": "PROD-001", "Price": 438.61, "CustomerEmail": "gisshlxfng@example.com"}, {"TransactionID": "TR-193", "Date": "11/04/2022", "Time": "01:56:29", "ProductID": "PROD-009", "Price": 570.19, "CustomerEmail": "weivuhqikw@example.com"}, {"TransactionID": "TR-194", "Date": "10/10/2022", "Time": "06:55:10", "ProductID": "PROD-004", "Price": 186.14, "CustomerEmail": "bsszhozlvk@example.com"}, {"TransactionID": "TR-195", "Date": "06/04/2022", "Time": "07:15:24", "ProductID": "PROD-004", "Price": 957.03, "CustomerEmail": "hehovffjua@example.com"}, {"TransactionID": "TR-196", "Date": "09/29/2022", "Time": "13:52:45", "ProductID": "PROD-005", "Price": 355.06, "CustomerEmail": "lngcfmewek@example.com"}, {"TransactionID": "TR-197", "Date": "01/11/2023", "Time": "11:48:09", "ProductID": "PROD-007", "Price": 74.1, "CustomerEmail": "vxzrmxfzij@example.com"}, {"TransactionID": "TR-198", "Date": "04/15/2023", "Time": "00:02:14", "ProductID": "PROD-005", "Price": 69.63, "CustomerEmail": "olcrifdfuj@example.com"}, {"TransactionID": "TR-199", "Date": "07/13/2022", "Time": "01:20:11", "ProductID": "PROD-002", "Price": 963.42, "CustomerEmail": "fhkuehkiej@example.com"}, {"TransactionID": "TR-200", "Date": "06/10/2022", "Time": "03:57:58", "ProductID": "PROD-006", "Price": 410.06, "CustomerEmail": "rpucfwgzid@example.com"}, {"TransactionID": "TR-104", "Date": "12/14/2022", "Time": "12:17:37", "ProductID": "PROD-005", "Price": 58.47, "CustomerEmail": "ugqickbbgt@example.com"}, {"TransactionID": "TR-111", "Date": "03/08/2023", "Time": "12:12:59", "ProductID": "PROD-007", "Price": 448.08, "CustomerEmail": "haqbcsaeep@example.com"}, {"TransactionID": "TR-005", "Date": "07/17/2022", "Time": "21:16:08", "ProductID": "PROD-007", "Price": 597.81, "CustomerEmail": "fbkddcdyvu@example.com"}, {"TransactionID": "TR-100", "Date": "06/03/2022", "Time": "23:55:26", "ProductID": "PROD-007", "Price": 108.27, "CustomerEmail": "hyqfdcapdp@example.com"}, {"TransactionID": "TR-076", "Date": "10/13/2022", "Time": "06:16:55", "ProductID": "PROD-005", "Price": 312.05, "CustomerEmail": "bksreixctc@example.com"}, {"TransactionID": "TR-183", "Date": "03/28/2023", "Time": "20:36:21", "ProductID": "PROD-009", "Price": 227.24, "CustomerEmail": "qofbrdlmxd@example.com"}, {"TransactionID": "TR-010", "Date": "08/26/2022", "Time": "16:34:08", "ProductID": "PROD-009", "Price": 273.9, "CustomerEmail": "rtidsliinj@example.com"}, {"TransactionID": "TR-075", "Date": "09/08/2022", "Time": "07:58:13", "ProductID": "PROD-009", "Price": 283.5, "CustomerEmail": "bthqiojjkl@example.com"}, {"TransactionID": "TR-150", "Date": "05/10/2023", "Time": "12:02:59", "ProductID": "PROD-009", "Price": 745.38, "CustomerEmail": "efkhuyhdek@example.com"}, {"TransactionID": "TR-150", "Date": "05/10/2023", "Time": "12:02:59", "ProductID": "PROD-009", "Price": 745.38, "CustomerEmail": "efkhuyhdek@example.com"}]
